flownat/__init__.py
flownat/core.py
flownat/parameters.yml
flownat/plot.py
flownat/datasets/catchment_delineation_rec.pkl.xz
flownat/tests/__init__.py
flownat/tests/test_FlowNat.py
flownat/tests/utest_ash_2019-07-19.py
flownat/tests/working.py
FlowNaturalisation-0.1.9.dist-info/LICENSE.txt
FlowNaturalisation-0.1.9.dist-info/METADATA
FlowNaturalisation-0.1.9.dist-info/WHEEL
FlowNaturalisation-0.1.9.dist-info/top_level.txt
FlowNaturalisation-0.1.9.dist-info/RECORD
