Metadata-Version: 2.1
Name: FlowNaturalisation
Version: 0.1.9
Summary: Tools to perform flow naturalisation in Caterbury
Home-page: https://github.com/Data-to-Knowledge/FlowNaturalisation
Author: Mike Kittridge
Author-email: mullenkamp1@gmail.com
License: Apache
Keywords: flow naturalisation
Platform: UNKNOWN
Classifier: Development Status :: 3 - Alpha
Classifier: Intended Audience :: Developers
Classifier: Topic :: Software Development :: Build Tools
Classifier: License :: OSI Approved :: Apache Software License
Classifier: Programming Language :: Python :: 2
Classifier: Programming Language :: Python :: 2.7
Classifier: Programming Language :: Python :: 3
Classifier: Programming Language :: Python :: 3.4
Classifier: Programming Language :: Python :: 3.5
Classifier: Programming Language :: Python :: 3.6
Requires-Dist: pdsql
Requires-Dist: gistools
Requires-Dist: requests
Requires-Dist: ecanallousagetools
Requires-Dist: hydrolm
Requires-Dist: pyyaml
Requires-Dist: geopandas (==0.7.0)
